nacos_client/__init__.py
nacos_client/gd_nacos_sdk.py
nacos_client_gd-0.3.0.dist-info/METADATA
nacos_client_gd-0.3.0.dist-info/WHEEL
nacos_client_gd-0.3.0.dist-info/top_level.txt
nacos_client_gd-0.3.0.dist-info/RECORD
