Metadata-Version: 2.1
Name: nacos-client-gd
Version: 0.3.0
Summary: 自定义的Nacos 3.1.0客户端库，支持配置查询/修改、服务实例查询
Home-page: https://github.com/baoqian188_baoqian/nacos-client-custom
Author: baoqian
Author-email: baoqian188@163.com
Classifier: Programming Language :: Python :: 3
Classifier: License :: OSI Approved :: MIT License
Classifier: Operating System :: OS Independent
Requires-Python: >=3.8
Requires-Dist: requests >=2.31.0
Requires-Dist: pyyaml >=6.0.1
